supervisord_mcp/__init__.py
supervisord_mcp/cli.py
supervisord_mcp/main.py
supervisord_mcp/manager.py
supervisord_mcp/mcp_server.py
supervisord_mcp-1.0.0.dist-info/licenses/LICENSE
supervisord_mcp-1.0.0.dist-info/METADATA
supervisord_mcp-1.0.0.dist-info/WHEEL
supervisord_mcp-1.0.0.dist-info/entry_points.txt
supervisord_mcp-1.0.0.dist-info/top_level.txt
supervisord_mcp-1.0.0.dist-info/RECORD
