Metadata-Version: 2.4
Name: supervisord-mcp
Version: 1.0.0
Summary: Supervisord process management tool with MCP integration
Author-email: AetherPlatform <aether-platform@re-x.info>
License-Expression: MIT
Project-URL: Homepage, https://github.com/aether-platform/supervisord-mcp
Project-URL: Repository, https://github.com/aether-platform/supervisord-mcp.git
Project-URL: Bug Tracker, https://github.com/aether-platform/supervisord-mcp/issues
Keywords: supervisord,mcp,process-management,asyncio
Classifier: Development Status :: 5 - Production/Stable
Classifier: Intended Audience :: Developers
Classifier: Programming Language :: Python :: 3
Classifier: Programming Language :: Python :: 3.10
Classifier: Programming Language :: Python :: 3.11
Classifier: Programming Language :: Python :: 3.12
Classifier: Topic :: System :: Systems Administration
Classifier: Topic :: Software Development :: Libraries :: Python Modules
Requires-Python: >=3.10
License-File: LICENSE
Requires-Dist: supervisor>=4.2.0
Requires-Dist: mcp>=1.1.0
Requires-Dist: click>=8.1.0
Requires-Dist: psutil>=5.9.0
Provides-Extra: dev
Requires-Dist: pytest>=7.4.0; extra == "dev"
Requires-Dist: pytest-asyncio>=0.21.0; extra == "dev"
Requires-Dist: pytest-cov>=4.1.0; extra == "dev"
Requires-Dist: ruff>=0.1.0; extra == "dev"
Requires-Dist: mypy>=1.5.0; extra == "dev"
Requires-Dist: pre-commit>=3.0.0; extra == "dev"
Provides-Extra: logging
Requires-Dist: colorlog>=6.7.0; extra == "logging"
Requires-Dist: structlog>=23.1.0; extra == "logging"
Dynamic: license-file
